jira_utils_package/__init__.py
jira_utils_package/jira_utils.py
jira_utils_package-0.1.dist-info/METADATA
jira_utils_package-0.1.dist-info/WHEEL
jira_utils_package-0.1.dist-info/top_level.txt
jira_utils_package-0.1.dist-info/RECORD
